sapientml_loaddata/__init__.py
sapientml_loaddata/generator.py
sapientml_loaddata/lib/sample_dataset.py
sapientml_loaddata/templates/concat_train_validation.py.jinja
sapientml_loaddata/templates/drop_ignore_columns.py.jinja
sapientml_loaddata/templates/loaddata.py.jinja
sapientml_loaddata/templates/loaddata_predict.py.jinja
sapientml_loaddata/templates/loaddata_train.py.jinja
sapientml_loaddata/templates/set_index.py.jinja
sapientml_loaddata/templates/set_validation_as_test.py.jinja
sapientml_loaddata/templates/split.py.jinja
sapientml_loaddata/templates/subsample.py.jinja
sapientml_loaddata-0.4.3.dist-info/LICENSE
sapientml_loaddata-0.4.3.dist-info/METADATA
sapientml_loaddata-0.4.3.dist-info/WHEEL
sapientml_loaddata-0.4.3.dist-info/entry_points.txt
sapientml_loaddata-0.4.3.dist-info/RECORD
