Metadata-Version: 2.1
Name: sapientml-loaddata
Version: 0.4.3
Summary: A SapientML plugin of CodeBlockGenerator for loading dataset
License: Apache-2.0
Author: The SapientML Authors
Maintainer: Kosaku Kimura
Maintainer-email: kimura.kosaku@fujitsu.com
Requires-Python: >=3.10,<3.13
Classifier: License :: OSI Approved :: Apache Software License
Classifier: Programming Language :: Python :: 3
Classifier: Programming Language :: Python :: 3.10
Classifier: Programming Language :: Python :: 3.11
Requires-Dist: jinja2 (>=3.1.2,<4.0.0)
Requires-Dist: sapientml
Requires-Dist: scikit-learn (>=1.3.2,<2.0.0)
